{
  "api": {
    "taskAppAPI": {
      "dependsOn": [
        {
          "attributes": [
            "Name",
            "Arn"
          ],
          "category": "function",
          "resourceName": "taskAppAPICreateTask"
        }
      ],
      "providerPlugin": "awscloudformation",
      "service": "API Gateway"
    }
  },
  "auth": {
    "taskapp1d5bac24": {
      "customAuth": false,
      "dependsOn": [],
      "frontendAuthConfig": {
        "mfaConfiguration": "OFF",
        "mfaTypes": [
          "SMS"
        ],
        "passwordProtectionSettings": {
          "passwordPolicyCharacters": [],
          "passwordPolicyMinLength": 8
        },
        "signupAttributes": [
          "EMAIL"
        ],
        "socialProviders": [],
        "usernameAttributes": [
          "EMAIL"
        ],
        "verificationMechanisms": [
          "EMAIL"
        ]
      },
      "providerPlugin": "awscloudformation",
      "service": "Cognito"
    }
  },
  "function": {
    "taskAppAPICreateTask": {
      "build": true,
      "providerPlugin": "awscloudformation",
      "service": "Lambda"
    },
    "taskappAPI": {
      "build": true,
      "providerPlugin": "awscloudformation",
      "service": "Lambda"
    }
  },
  "hosting": {
    "S3AndCloudFront": {
      "providerPlugin": "awscloudformation",
      "service": "S3AndCloudFront"
    }
  },
  "parameters": {
    "AMPLIFY_function_taskAppAPICreateTask_deploymentBucketName": {
      "usedBy": [
        {
          "category": "function",
          "resourceName": "taskAppAPICreateTask"
        }
      ]
    },
    "AMPLIFY_function_taskAppAPICreateTask_s3Key": {
      "usedBy": [
        {
          "category": "function",
          "resourceName": "taskAppAPICreateTask"
        }
      ]
    },
    "AMPLIFY_function_taskappAPI_deploymentBucketName": {
      "usedBy": [
        {
          "category": "function",
          "resourceName": "taskappAPI"
        }
      ]
    },
    "AMPLIFY_function_taskappAPI_s3Key": {
      "usedBy": [
        {
          "category": "function",
          "resourceName": "taskappAPI"
        }
      ]
    }
  },
  "storage": {
    "taskAppDB": {
      "providerPlugin": "awscloudformation",
      "service": "DynamoDB"
    }
  }
}